{"name": "Racismo", "id": 109224, "predecessors": [{"name": "Preconceitos_e_discriminações", "id": 494407}, {"name": "Violações_dos_direitos_humanos", "id": 2009480}, {"name": "Sociologia", "id": 21974}, {"name": "Antropologia", "id": 19981}], "successors": [{"name": "Escravidão", "id": 15867}, {"name": "Nazismo", "id": 15926}, {"name": "Filmes_com_temática_etnorracial", "id": 848956}, {"name": "Racismo_científico", "id": 1335754}, {"name": "Neofascismo", "id": 1378368}, {"name": "Neonazismo", "id": 2058044}, {"name": "Antissemitismo", "id": 2139519}, {"name": "Antirracismo", "id": 4106357}, {"name": "Nazismo_nos_Estados_Unidos", "id": 5435652}, {"name": "Nacionalismo_branco", "id": 5808748}, {"name": "Supremacia_branca", "id": 6490920}, {"name": "História_da_segregação_racial_nos_Estados_Unidos", "id": 6329361}]}