{"name": "Astronomia", "id": 14983, "predecessors": [{"name": "Ciência", "id": 40676}, {"name": "Ciências_aplicadas", "id": 15791}], "successors": [{"name": "Calendários", "id": 15053}, {"name": "História_da_astronomia", "id": 271562}, {"name": "!Predefinições_sobre_astronomia", "id": 361142}, {"name": "Objetos_astronómicos", "id": 2167900}, {"name": "Organizações_de_astronomia", "id": 2460515}, {"name": "Prêmios_de_astronomia", "id": 2894212}, {"name": "Listas_de_astronomia", "id": 3248706}, {"name": "Instrumentos_astronômicos", "id": 3255984}, {"name": "Conceitos_de_astronomia", "id": 7165474}, {"name": "Astrônomas", "id": 3701839}, {"name": "Cientistas_planetários", "id": 3902732}, {"name": "Astrônomos_do_Brasil", "id": 349526}, {"name": "Programa_espacial_brasileiro", "id": 1149229}, {"name": "Chuvas_de_meteoros", "id": 399303}, {"name": "Supernovas", "id": 587387}, {"name": "Planetologia", "id": 15920}, {"name": "Cosmologia", "id": 49046}, {"name": "Astrofísica", "id": 51776}, {"name": "Mecânica_celeste", "id": 129496}, {"name": "Astrometria", "id": 599295}, {"name": "Astronomia_estelar", "id": 1093162}, {"name": "Astrobiologia", "id": 1116888}, {"name": "Astronomia_observacional", "id": 2923718}, {"name": "Quasares", "id": 607472}, {"name": "Radiotelescópios", "id": 1801414}, {"name": "SETI", "id": 3472143}, {"name": "Sistema_Solar", "id": 15113}, {"name": "Filmes_sobre_Marte_e/ou_marcianos", "id": 2860818}, {"name": "Filmes_sobre_extraterrestres", "id": 3609130}, {"name": "Medalha_de_Ouro_da_Royal_Astronomical_Society", "id": 2645955}, {"name": "Medalha_Bruce", "id": 3236212}, {"name": "Prémio_Dannie_Heineman_de_astrofísica", "id": 5044000}, {"name": "Catálogos_astronômicos", "id": 562196}, {"name": "Livros_de_astronomia", "id": 2041831}, {"name": "Periódicos_de_astronomia", "id": 3423005}, {"name": "Matéria_escura", "id": 599302}, {"name": "Candidatos_a_planeta_anão", "id": 3337904}, {"name": "Vida_extraterrestre", "id": 6156759}, {"name": "Braço_de_Orion-Cygnus", "id": 7132952}]}