{"name": "Cultura_da_cidade_de_Nova_Iorque", "id": 1743361, "predecessors": [{"name": "Cidades_dos_Estados_Unidos", "id": 57025}, {"name": "Subdivisões_administrativas_de_países_de_primeiro_nível", "id": 3648377}, {"name": "Geografia_política", "id": 473490}], "successors": [{"name": "Filmes_gravados_em_Nova_Iorque", "id": 3300514}, {"name": "Séries_de_televisão_ambientadas_em_Nova_Iorque", "id": 3655133}, {"name": "Filmes_ambientados_em_Nova_Iorque", "id": 3814734}, {"name": "Bandas_de_punk_rock", "id": 238862}, {"name": "Músicos_de_punk_rock", "id": 266624}, {"name": "Álbuns_de_punk_rock", "id": 308963}, {"name": "Canções_de_punk_rock", "id": 2449652}, {"name": "Broadway", "id": 2034991}, {"name": "Filmes_ambientados_em_Manhattan", "id": 4372136}, {"name": "Museus_de_Manhattan", "id": 5364271}, {"name": "Registro_Nacional_de_Lugares_Históricos_em_Manhattan", "id": 7101714}]}