{"name": "Anura", "id": 205086, "predecessors": [{"name": "Anfíbios", "id": 51012}], "successors": [{"name": "Ranidae", "id": 252771}, {"name": "Bufonidae", "id": 398571}, {"name": "Dendrobatidae", "id": 990768}, {"name": "Myobatrachidae", "id": 1299292}, {"name": "Hilídeos", "id": 1326338}, {"name": "Rhacophoridae", "id": 1375513}, {"name": "Microhylidae", "id": 1381514}, {"name": "Arthroleptidae", "id": 1390950}, {"name": "Phrynobatrachus", "id": 1391884}, {"name": "Mantellidae", "id": 1393170}, {"name": "Centrolenídeos", "id": 2561935}, {"name": "Craugastoridae", "id": 3493903}, {"name": "Dicroglossidae", "id": 4583616}, {"name": "Leptodactylus", "id": 1389529}, {"name": "Pseudopaludicola", "id": 1390848}, {"name": "Physalaemus", "id": 1392032}, {"name": "Leptobrachium", "id": 1389593}, {"name": "Xenophrys", "id": 1393175}, {"name": "Leptolalax", "id": 1393863}, {"name": "Brachycephalus", "id": 1390920}, {"name": "Ischnocnema", "id": 1393851}, {"name": "Gastrotheca", "id": 1392363}, {"name": "Allobates", "id": 4439532}, {"name": "Cycloramphus", "id": 1390673}, {"name": "Eleutherodactylus", "id": 1376409}, {"name": "Hylodes", "id": 1393843}, {"name": "Proceratophrys", "id": 1390805}, {"name": "Micrixalus", "id": 1393126}, {"name": "Ptychadena", "id": 1390876}, {"name": "Nyctibatrachus", "id": 1392643}, {"name": "Platymantis", "id": 1390658}, {"name": "Phyllomedusa", "id": 4119334}, {"name": "Litoria", "id": 1326336}]}