{"name": "Arquitetura_de_Portugal", "id": 2122470, "predecessors": [{"name": "Cultura_de_Portugal", "id": 58532}, {"name": "Arquitetura", "id": 15243}, {"name": "Arte", "id": 14871}], "successors": [{"name": "Arquitetos_de_Portugal", "id": 59089}, {"name": "Monumentos_de_Portugal", "id": 71980}, {"name": "Barragens_de_Portugal", "id": 107812}, {"name": "Bibliotecas_de_Portugal", "id": 302934}, {"name": "Hospitais_de_Portugal", "id": 372147}, {"name": "Fontes_e_chafarizes_de_Portugal", "id": 1962829}, {"name": "Pavilhões_de_Portugal", "id": 2146070}, {"name": "Locais_de_espetáculo_em_Portugal", "id": 2225343}, {"name": "Restaurantes_de_Portugal", "id": 2268493}, {"name": "Centros_culturais_de_Portugal", "id": 2433055}, {"name": "Listas_de_património_de_Portugal", "id": 65102}, {"name": "!Predefinições_sobre_património_de_Portugal", "id": 3200541}, {"name": "Igrejas_classificadas_como_imóvel_de_interesse_público_em_Portugal", "id": 961361}, {"name": "Castelos_classificados_como_imóvel_de_interesse_público_em_Portugal", "id": 1026455}, {"name": "Megálitos_classificados_como_imóvel_de_interesse_público_em_Portugal", "id": 1026460}, {"name": "Pelourinhos_classificados_como_imóvel_de_interesse_público_em_Portugal", "id": 1646367}, {"name": "Torres_classificadas_como_imóvel_de_interesse_público_em_Portugal", "id": 1664757}, {"name": "Fortificações_classificadas_como_imóvel_de_interesse_público_em_Portugal", "id": 5577167}, {"name": "Capelas_classificadas_como_imóvel_de_interesse_público_em_Portugal", "id": 5577168}, {"name": "Palácios_classificados_como_imóvel_de_interesse_público_em_Portugal", "id": 5577171}, {"name": "Pontes_classificadas_como_imóvel_de_interesse_público_em_Portugal", "id": 5577181}, {"name": "Edifícios_monásticos_cristãos_classificados_como_imóvel_de_interesse_público_em_Portugal", "id": 5577192}, {"name": "Casas_classificadas_como_imóvel_de_interesse_público_em_Portugal", "id": 5577195}, {"name": "Imóveis_de_interesse_público_nos_Açores", "id": 6223040}, {"name": "Sítios_arqueológicos_romanos_classificados_como_imóvel_de_interesse_público_em_Portugal", "id": 6878974}, {"name": "Património_edificado_em_Lisboa", "id": 1381616}, {"name": "Património_edificado_em_Oeiras", "id": 1446602}, {"name": "Património_edificado_em_Sintra", "id": 1446603}, {"name": "Igrejas_do_Porto", "id": 534643}, {"name": "Património_edificado_no_Porto", "id": 1463789}, {"name": "Solares_de_Portugal", "id": 159927}, {"name": "Quintas_de_Portugal", "id": 252805}, {"name": "Residências_reais_de_Portugal", "id": 2787735}, {"name": "Palacetes_de_Portugal", "id": 5577202}, {"name": "Museus-casas_de_Portugal", "id": 5966887}, {"name": "Povoações_romanas_em_Portugal", "id": 95802}, {"name": "Estilo_manuelino", "id": 1168823}, {"name": "Arte_Nova_em_Portugal", "id": 6666539}, {"name": "Igrejas_românicas_em_Portugal", "id": 4858196}, {"name": "Rota_do_Românico", "id": 5054930}, {"name": "Igrejas_góticas_em_Portugal", "id": 4858211}, {"name": "Prémio_Valmor", "id": 3496384}, {"name": "Arquitetura_colonial_no_Brasil", "id": 2206524}, {"name": "Igrejas_de_Portugal_do_século_XVI", "id": 5592303}, {"name": "Arquitetos_de_Portugal_do_século_XX", "id": 5511379}, {"name": "Portos_de_Portugal", "id": 77637}, {"name": "Fortificações_costeiras_em_Portugal", "id": 6344889}, {"name": "Faróis_dos_Açores", "id": 1138739}, {"name": "Imóveis_de_interesse_público_no_distrito_do_Porto", "id": 5929928}, {"name": "Imóveis_de_interesse_público_no_distrito_de_Lisboa", "id": 5929937}, {"name": "Imóveis_de_interesse_público_no_distrito_de_Viana_do_Castelo", "id": 5935933}, {"name": "Imóveis_de_interesse_público_no_distrito_de_Beja", "id": 6057579}, {"name": "Imóveis_de_interesse_público_no_distrito_de_Faro", "id": 6119869}, {"name": "Imóveis_de_interesse_público_no_distrito_de_Bragança", "id": 6119878}, {"name": "Imóveis_de_interesse_público_no_distrito_de_Coimbra", "id": 6119880}, {"name": "Imóveis_de_interesse_público_no_distrito_da_Guarda", "id": 6119881}, {"name": "Imóveis_de_interesse_público_no_distrito_de_Évora", "id": 6119889}, {"name": "Imóveis_de_interesse_público_em_Braga", "id": 5931644}, {"name": "Pelourinhos_no_distrito_de_Bragança", "id": 6047641}, {"name": "Pelourinhos_no_distrito_de_Castelo_Branco", "id": 6121464}, {"name": "Pelourinhos_no_distrito_de_Coimbra", "id": 6121466}, {"name": "Pelourinhos_no_distrito_de_Viseu", "id": 6122439}, {"name": "Pontes_no_distrito_de_Faro", "id": 6269770}, {"name": "Pontes_no_distrito_de_Beja", "id": 6269773}, {"name": "Residências_do_distrito_de_Viseu", "id": 6343996}, {"name": "Residências_do_distrito_do_Porto", "id": 6343997}, {"name": "Residências_do_distrito_de_Viana_do_Castelo", "id": 6344007}, {"name": "Fortificações_do_distrito_de_Faro", "id": 6344972}, {"name": "Monumentos_de_interesse_público_no_distrito_de_Lisboa", "id": 6387140}, {"name": "Monumentos_de_interesse_público_no_distrito_do_Porto", "id": 6387144}, {"name": "Antigas_fortificações_de_Portugal", "id": 2051802}]}