{"name": "Esporte_universitário_dos_Estados_Unidos", "id": 2529732, "predecessors": [{"name": "Cultura_dos_Estados_Unidos", "id": 2497006}, {"name": "Qualidade", "id": 456269}], "successors": [{"name": "Universidade_Harvard", "id": 2041733}, {"name": "Professores_da_Universidade_Cornell", "id": 2017937}, {"name": "Alunos_da_Universidade_Cornell", "id": 2017942}, {"name": "Professores_do_Dartmouth_College", "id": 2932402}, {"name": "Alunos_do_Dartmouth_College", "id": 2932415}, {"name": "Alunos_da_Universidade_de_Indiana", "id": 2986740}, {"name": "Professores_da_Universidade_de_Indiana", "id": 3367360}, {"name": "Alunos_da_Universidade_Rutgers", "id": 3006350}, {"name": "Professores_da_Universidade_Rutgers", "id": 3485105}, {"name": "Alunos_da_Universidade_George_Washington", "id": 2830682}]}