{"name": "!Wikipedistas_bem-humorados", "id": 2669556, "predecessors": [{"name": "Conteúdo", "id": 2147069}], "successors": [{"name": "!Usuários_na_Desciclopédia", "id": 602805}, {"name": "!Wikipedistas_que_são_uma_forma_de_vida_baseada_em_carbono", "id": 649452}, {"name": "!Wikipedistas_que_são_vilões_e_querem_conquistar_o_mundo", "id": 649467}, {"name": "!Wikipedistas_que_sabem_que_cookie_é_bom", "id": 2571152}, {"name": "!Wikipedistas_que_mantêm_o_bom_humor_e_sabem_rir_de_si_mesmos", "id": 2669337}, {"name": "!Wikipedistas_que_já_foram_espermatozoides_bem-sucedidos", "id": 2674817}, {"name": "!Usuários_mamíferos", "id": 3335650}]}