{"name": "Guerras_Cantábricas", "id": 4920932, "predecessors": [{"name": "Augusto", "id": 4149220}, {"name": "Batalhas_do_século_I_a.C.", "id": 2442949}, {"name": "Conquista_romana_da_Hispânia", "id": 5304769}, {"name": "Regiões_linguísticas", "id": 2106841}, {"name": "Geografia_da_Europa", "id": 98530}, {"name": "Anos_do_século_I_a.C.", "id": 17852}, {"name": "Conteúdo", "id": 2147069}, {"name": "Século_I_a.C.", "id": 17848}, {"name": "Campos_da_história", "id": 2659436}, {"name": "Tecnologia_militar", "id": 3152026}], "successors": []}