{"name": "América", "id": 55017, "predecessors": [{"name": "Continentes", "id": 15421}], "successors": [{"name": "História_da_América", "id": 95119}, {"name": "Geografia_da_América", "id": 259057}, {"name": "Listas_da_América", "id": 2260574}, {"name": "Escravidão_no_Novo_Mundo", "id": 3185820}, {"name": "América_do_Norte", "id": 15759}, {"name": "América_do_Sul", "id": 18889}, {"name": "América_Central", "id": 25281}, {"name": "América_Latina", "id": 144587}, {"name": "Mesoamérica", "id": 1034573}, {"name": "Ibero-América", "id": 2098461}, {"name": "Moedas_da_América", "id": 838771}, {"name": "!Portal_América", "id": 3205496}, {"name": "!Portal_México", "id": 2314440}, {"name": "!Portal_Granada", "id": 3205424}, {"name": "!Portal_Bermudas", "id": 2373629}, {"name": "!Portal_Gronelândia", "id": 5641916}, {"name": "!Portal_Argentina", "id": 2316734}, {"name": "!Portal_Bolívia", "id": 2363031}, {"name": "!Portais_sobre_o_Brasil", "id": 2373375}, {"name": "!Portal_Chile", "id": 2379014}, {"name": "!Portal_Guiana", "id": 3205541}, {"name": "!Portal_Paraguai", "id": 3206736}, {"name": "!Portal_Peru", "id": 3206753}, {"name": "!Portal_Uruguai", "id": 3207085}, {"name": "!Portal_Venezuela", "id": 3207103}, {"name": "!Portal_Suriname", "id": 3207169}, {"name": "!Portal_Equador", "id": 3556231}, {"name": "!Portal_Ilhas_Malvinas", "id": 5641755}, {"name": "!Portal_Amazônia", "id": 7171205}, {"name": "!Portal_Antígua_e_Barbuda", "id": 2373618}, {"name": "!Portal_Bahamas", "id": 2373625}, {"name": "!Portal_Belize", "id": 2373628}, {"name": "!Portal_Haiti", "id": 2917451}, {"name": "!Portal_Guatemala", "id": 3205516}, {"name": "!Portal_Honduras", "id": 3205549}, {"name": "!Portal_Jamaica", "id": 3205574}, {"name": "!Portal_Nicarágua", "id": 3206633}, {"name": "!Portal_Panamá", "id": 3206716}, {"name": "!Portal_Porto_Rico", "id": 3206776}, {"name": "!Portal_República_Dominicana", "id": 3206815}, {"name": "!Portal_Santa_Lúcia", "id": 3207040}, {"name": "!Portal_São_Cristóvão_e_Neves", "id": 3207198}, {"name": "!Portal_Trindade_e_Tobago", "id": 3207256}, {"name": "!Portal_El_Salvador", "id": 3701192}, {"name": "!Portal_Cuba", "id": 3701193}, {"name": "!Portal_Dominica", "id": 3706309}, {"name": "!Portal_Costa_Rica", "id": 3706311}, {"name": "!Portal_São_Vicente_e_Granadinas", "id": 3723915}, {"name": "Política_da_América", "id": 2260568}, {"name": "Línguas_da_América", "id": 2213716}, {"name": "Cultura_da_América_do_Sul", "id": 2229776}, {"name": "Cultura_da_América_Latina", "id": 2417950}, {"name": "Cultura_dos_ameríndios", "id": 2515517}, {"name": "Culinária_da_América_Central", "id": 2192330}, {"name": "Culinária_da_América_Latina", "id": 4419083}, {"name": "Esporte_da_América_Central", "id": 104701}, {"name": "Organizações_esportivas_da_América", "id": 2106064}, {"name": "Desporto_da_América_do_Sul", "id": 2254769}, {"name": "Competições_desportivas_da_América", "id": 5513359}, {"name": "Bolsa_Guggenheim", "id": 3754258}, {"name": "Música_da_Jamaica", "id": 64361}, {"name": "Música_de_Cuba", "id": 179457}, {"name": "Músicos_de_Porto_Rico", "id": 293486}, {"name": "Álbuns_de_Ricky_Martin", "id": 2240989}, {"name": "Álbuns_de_Calle_13", "id": 3899757}, {"name": "Álbuns_de_Luis_Fonsi", "id": 5485758}, {"name": "Organizações_regionais_da_América", "id": 1954392}, {"name": "Organizações_sediadas_no_Canadá", "id": 2623708}, {"name": "Transportes_do_Brasil", "id": 475813}, {"name": "Pontes_do_Uruguai", "id": 1892975}, {"name": "Aeroportos_da_Bolívia", "id": 1103099}, {"name": "Aeroportos_do_Suriname", "id": 1133439}, {"name": "Aeroportos_do_Equador", "id": 1150181}, {"name": "Transportes_do_Canadá", "id": 155364}, {"name": "Transportes_dos_Estados_Unidos", "id": 2497571}, {"name": "Demografia_da_América_do_Sul", "id": 1499691}, {"name": "Povos_do_continente_americano", "id": 1929682}, {"name": "Grupos_étnicos_da_América_do_Norte", "id": 2059638}, {"name": "Latino-americanos", "id": 2489574}, {"name": "!Portal_Califórnia", "id": 2964453}, {"name": "!Portal_Texas", "id": 2966428}, {"name": "!Portal_Nova_Iorque", "id": 2986186}, {"name": "!Portal_Flórida", "id": 3011927}, {"name": "!Portal_Estados_Unidos", "id": 3050241}, {"name": "!Portal_Utah", "id": 3246201}, {"name": "!Portal_Arizona", "id": 3324301}, {"name": "!Portal_Minnesota", "id": 3494878}, {"name": "!Portal_Nova_Jérsia", "id": 4123066}, {"name": "!Portal_Havaí", "id": 5629670}, {"name": "!Portal_Ohio", "id": 6451756}, {"name": "Transporte_ferroviário_no_Brasil", "id": 1844385}, {"name": "Empresas_ferroviárias_da_Argentina", "id": 2541706}, {"name": "Metrô_de_Caracas", "id": 854977}, {"name": "Metrô_de_São_Paulo", "id": 176319}, {"name": "Metrô_do_Rio_de_Janeiro", "id": 346071}, {"name": "Metrô_de_Salvador", "id": 879706}, {"name": "Metrô_do_Distrito_Federal_(Brasil)", "id": 1052235}, {"name": "Metrô_de_Belo_Horizonte", "id": 1067160}, {"name": "Metrô_de_Fortaleza", "id": 1067161}, {"name": "Metrô_de_Porto_Alegre", "id": 1067168}, {"name": "Metrô_do_Recife", "id": 1285884}, {"name": "!Predefinições_sobre_metropolitanos_do_Brasil", "id": 3552590}, {"name": "Metrô_de_Medellín", "id": 2939671}, {"name": "Metro_de_Santiago_(Chile)", "id": 2927583}, {"name": "Metro_de_Buenos_Aires", "id": 2927907}, {"name": "Empresas_ferroviárias_do_Canadá", "id": 2541727}, {"name": "Metropolitanos_dos_Estados_Unidos", "id": 2518607}, {"name": "Empresas_ferroviárias_dos_Estados_Unidos", "id": 2518613}, {"name": "Trens_ligeiros_dos_Estados_Unidos", "id": 5745964}, {"name": "Trens_suburbanos_dos_Estados_Unidos", "id": 5746017}, {"name": "Metro_de_Montreal", "id": 1116160}, {"name": "Metrô_de_Toronto", "id": 4875745}, {"name": "Metrô_da_Cidade_do_México", "id": 1937096}, {"name": "VLT_de_Guadalajara", "id": 4812076}, {"name": "Metrorrey", "id": 4812077}, {"name": "Histórias_em_quadrinhos_do_Brasil", "id": 858864}, {"name": "Banda_desenhada_dos_Estados_Unidos", "id": 2497007}, {"name": "Banda_desenhada_do_Canadá", "id": 3610606}, {"name": "Cartunistas_da_Argentina", "id": 227999}, {"name": "Autores_de_banda_desenhada_da_Argentina", "id": 2348139}, {"name": "Portos_dos_Estados_Unidos", "id": 2519844}, {"name": "Navios_dos_Estados_Unidos", "id": 2575650}, {"name": "Canais_dos_Estados_Unidos", "id": 2654994}, {"name": "Portos_do_México", "id": 3711400}, {"name": "Transporte_hidroviário_no_Brasil", "id": 1844416}, {"name": "Portos_da_Argentina", "id": 1034296}, {"name": "Navios_de_guerra_da_Argentina", "id": 3169489}, {"name": "Contratorpedeiros_da_Marinha_da_Argentina", "id": 3690561}, {"name": "Aviação_nos_Estados_Unidos", "id": 2519846}, {"name": "Empresas_aéreas_do_Canadá", "id": 566470}, {"name": "Empresas_aéreas_do_México", "id": 570925}, {"name": "Empresas_aéreas_dos_Estados_Unidos", "id": 2519857}, {"name": "Aeroportos_do_Canadá", "id": 100552}, {"name": "Aviões_produzidos_no_Canadá", "id": 977788}, {"name": "Empresas_aeroespaciais_do_Canadá", "id": 2927574}, {"name": "Pontes_rodoviárias_de_Nova_Iorque", "id": 4322930}, {"name": "Pontes_rodoviárias_da_Califórnia", "id": 4323093}, {"name": "Pontes_internacionais_no_Brasil", "id": 7271337}, {"name": "Pontes_internacionais_entre_Brasil_e_Argentina", "id": 6346601}, {"name": "Pontes_sobre_o_rio_Paraná", "id": 2671833}, {"name": "Pontes_ferroviárias_do_Rio_Grande_do_Sul", "id": 4299557}, {"name": "Pontes_rodoviárias_do_Rio_Grande_do_Sul", "id": 4299572}, {"name": "Pontes_rodoviárias_do_Paraná", "id": 4299668}, {"name": "Pontes_rodoviárias_de_Mato_Grosso_do_Sul", "id": 4299657}, {"name": "Pontes_do_Recife", "id": 2595520}, {"name": "Pontes_rodoviárias_de_Roraima", "id": 4300182}, {"name": "Pontes_da_cidade_de_São_Paulo", "id": 2295826}, {"name": "Pontes_de_Ouro_Preto", "id": 6012959}, {"name": "Orquestras_do_Canadá", "id": 514430}, {"name": "Orquestras_dos_Estados_Unidos", "id": 2501359}, {"name": "Orquestras_do_México", "id": 4731927}, {"name": "Arquitetura_do_Brasil", "id": 2206525}, {"name": "Construções_da_Colômbia", "id": 975049}, {"name": "Monumentos_do_Peru", "id": 620392}, {"name": "Aeroportos_do_Peru", "id": 640412}, {"name": "Patrimônio_Mundial_da_UNESCO_no_Suriname", "id": 660666}, {"name": "Patrimônio_Mundial_da_UNESCO_na_Argentina", "id": 496862}, {"name": "Arquitetos_da_Argentina", "id": 2132051}, {"name": "Aeroportos_da_Argentina", "id": 282664}, {"name": "Museus_do_Chile", "id": 358001}, {"name": "Aeroportos_do_Chile", "id": 1143885}, {"name": "Palácios_do_Chile", "id": 1284573}, {"name": "Observatórios_astronômicos_do_Chile", "id": 2209138}, {"name": "Estradas_do_Chile", "id": 4574578}, {"name": "Arranha-céus_de_Buenos_Aires", "id": 5260046}, {"name": "Aeroportos_do_Uruguai", "id": 1029227}, {"name": "Fortificações_do_Paraguai", "id": 2051832}, {"name": "Construções_de_Buenos_Aires", "id": 2413974}, {"name": "Construções_de_La_Plata", "id": 5260394}, {"name": "Construções_de_Montevidéu", "id": 3495371}, {"name": "Arquitetura_do_México", "id": 2209471}, {"name": "Arquitetura_dos_Estados_Unidos", "id": 2497532}, {"name": "Arquitetos_do_Canadá", "id": 2183670}, {"name": "Shopping_centers_do_Canadá", "id": 374249}, {"name": "Museus_do_Canadá", "id": 533960}, {"name": "Bibliotecas_do_Canadá", "id": 1705757}, {"name": "Fortificações_do_Canadá", "id": 2050360}, {"name": "Estúdios_de_animação_do_Canadá", "id": 2313108}, {"name": "Filmes_ambientados_na_América_do_Sul", "id": 3805485}, {"name": "Filmes_ambientados_na_América_Central", "id": 3834553}, {"name": "Locomotivas_a_diesel_dos_Estados_Unidos", "id": 2518614}, {"name": "Locomotivas_elétricas_dos_Estados_Unidos", "id": 2518615}, {"name": "Locomotivas_diesel-elétricas_dos_Estados_Unidos", "id": 3382762}, {"name": "Locomotivas_a_vapor_dos_Estados_Unidos", "id": 3739870}, {"name": "Estações_do_Metrorrey", "id": 4819367}, {"name": "Estações_do_VLT_de_Guadalajara", "id": 4819486}, {"name": "Estações_do_Metrô_da_Cidade_do_México", "id": 4831092}, {"name": "Estações_do_Metrô_de_Montreal", "id": 4838472}, {"name": "Estações_do_Metrô_de_Toronto", "id": 4875751}, {"name": "Estações_do_Metrô_de_Baltimore", "id": 4875781}, {"name": "Estações_do_Metrô_de_Washington", "id": 4875808}, {"name": "Estações_do_Metrô_de_São_Paulo", "id": 875945}, {"name": "Estações_do_Metrô_do_Rio_de_Janeiro", "id": 3071286}, {"name": "Estações_do_Metrô_do_Distrito_Federal_(Brasil)", "id": 3898052}, {"name": "Estações_do_Metrô_de_Belo_Horizonte", "id": 4166161}, {"name": "Estações_do_Metrô_de_Porto_Alegre", "id": 4406116}, {"name": "Estações_do_Metrô_de_Salvador", "id": 4408975}, {"name": "Estações_do_Metrô_de_Fortaleza", "id": 4863795}, {"name": "Estações_do_Teleférico_do_Alemão", "id": 5458287}, {"name": "Estações_da_Linha_Centro_do_Metrô_do_Recife", "id": 5830095}, {"name": "Estações_da_Linha_Sul_do_Metrô_do_Recife", "id": 5830096}, {"name": "Estações_do_Metrô_de_Medellín", "id": 4838704}, {"name": "Estações_do_Metro_de_Santiago", "id": 4895478}, {"name": "Estações_do_Biotrén", "id": 4937955}, {"name": "Estações_do_Metrô_de_Valparaíso", "id": 4974809}, {"name": "Estações_do_Metro_de_Buenos_Aires", "id": 4844340}, {"name": "Estações_do_Metrô_de_Lima", "id": 4857459}, {"name": "Jogos_eletrônicos_ambientados_no_Brasil", "id": 3829130}, {"name": "Jogos_eletrônicos_ambientados_na_Argentina", "id": 3829144}, {"name": "Jogos_eletrônicos_ambientados_no_Peru", "id": 3829175}, {"name": "Jogos_eletrônicos_ambientados_na_Colômbia", "id": 3875605}, {"name": "Jogos_eletrônicos_ambientados_no_Chile", "id": 3878984}, {"name": "Jogos_eletrônicos_ambientados_em_Cuba", "id": 3875566}, {"name": "Jogos_eletrônicos_ambientados_no_Panamá", "id": 6443601}, {"name": "Primeira_Ferrovia_Transcontinental", "id": 4795845}, {"name": "!Portal_Canadá", "id": 2375904}, {"name": "!Portal_Quebec", "id": 5380312}, {"name": "Wilshire_Boulevard", "id": 5492861}, {"name": "Paradas_do_Metrotranvía_de_Mendoza", "id": 5472624}, {"name": "Estações_da_Tranvía_de_Ayacucho", "id": 5078323}, {"name": "Estações_do_VLT_da_Cidade_do_México", "id": 4849843}, {"name": "Estações_do_Trem_Suburbano_do_Vale_do_México", "id": 5626167}, {"name": "Pontes_sobre_o_rio_Uruguai", "id": 2671819}, {"name": "Acidentes_e_incidentes_aéreos_no_Brasil", "id": 851763}, {"name": "Acidentes_e_incidentes_ferroviários_no_Brasil", "id": 1926686}, {"name": "Mortes_em_acidentes_de_trânsito_no_Brasil", "id": 3860969}, {"name": "Acidentes_e_incidentes_aéreos_nos_Estados_Unidos", "id": 2519864}, {"name": "Acidentes_e_incidentes_aéreos_no_Canadá", "id": 4785950}, {"name": "Acidentes_e_incidentes_aéreos_no_México", "id": 4792347}, {"name": "Acidentes_e_incidentes_ferroviários_nos_Estados_Unidos", "id": 5867966}, {"name": "Empresas_aéreas_extintas_do_Canadá", "id": 2521716}, {"name": "Direito_do_Brasil", "id": 127438}, {"name": "Protocolo_de_Quioto", "id": 4250430}, {"name": "Casos_de_pessoas_desaparecidas_no_Brasil", "id": 6039707}, {"name": "Estações_da_PATH_em_Nova_Jérsei", "id": 6842396}]}