{"name": "Construção", "id": 59758, "predecessors": [{"name": "Engenharia", "id": 15244}], "successors": [{"name": "Arquitetura", "id": 15243}, {"name": "Construções", "id": 41684}, {"name": "Engenharia_civil", "id": 657967}, {"name": "Material_de_construção", "id": 1221204}, {"name": "Veículos_de_construção_e_engenharia", "id": 2204752}, {"name": "Arquitetura_militar", "id": 72861}, {"name": "Engenheiros_militares_de_Portugal", "id": 3919242}, {"name": "Construtoras_do_Brasil", "id": 1116674}, {"name": "Portos", "id": 77636}, {"name": "Ilhas_artificiais", "id": 668261}, {"name": "Fortificações_costeiras_em_Portugal", "id": 6344889}, {"name": "Acidentes_e_incidentes_aéreos_de_2021", "id": 6460229}, {"name": "Ataques_de_11_de_setembro_de_2001", "id": 2901958}, {"name": "Acidentes_e_incidentes_aéreos_de_2019", "id": 5915090}, {"name": "Acidentes_e_incidentes_aéreos_de_2016", "id": 4962532}, {"name": "Catacumbas_romanas", "id": 3871370}]}