{"name": "Artistas_da_Itália", "id": 620631, "predecessors": [{"name": "Geografia_política", "id": 473490}, {"name": "Arte", "id": 14871}, {"name": "Conteúdo", "id": 2147069}], "successors": [{"name": "Atores_da_Itália", "id": 62041}, {"name": "Escritores_da_Itália", "id": 94826}, {"name": "Cineastas_da_Itália", "id": 122750}, {"name": "Músicos_da_Itália", "id": 128783}, {"name": "Estilistas_da_Itália", "id": 164162}, {"name": "Fotógrafos_da_Itália", "id": 202749}, {"name": "Gravadores_da_Itália", "id": 1980525}, {"name": "Pintores_da_Itália", "id": 57620}, {"name": "Escultores_da_Itália", "id": 57623}, {"name": "Autores_de_banda_desenhada_da_Itália", "id": 1055701}]}