{"name": "Metrologia", "id": 63979, "predecessors": [{"name": "Ciências_aplicadas", "id": 15791}, {"name": "Padrões", "id": 31822}], "successors": [{"name": "Unidades_de_medida", "id": 25003}, {"name": "Grandezas_físicas", "id": 39788}, {"name": "Instrumentos_de_medida", "id": 63277}, {"name": "Astrometria", "id": 599295}, {"name": "Probabilidade_e_estatística", "id": 1051994}, {"name": "Psicometria", "id": 1301466}, {"name": "Medição_do_tempo", "id": 1432436}, {"name": "Relógios", "id": 349580}]}