{"name": "Parlamento", "id": 843767, "predecessors": [{"name": "Governo", "id": 128056}, {"name": "Direito_constitucional", "id": 25655}], "successors": [{"name": "Parlamentos_por_país", "id": 1061347}, {"name": "Parlamentos_extintos", "id": 4867598}, {"name": "Assembleias_legislativas_do_Brasil", "id": 2150461}, {"name": "Câmaras_municipais_do_Brasil", "id": 408373}, {"name": "Paços_do_concelho_de_Portugal", "id": 2392290}, {"name": "Câmaras_altas_nacionais", "id": 2117568}, {"name": "Senadores_da_Itália", "id": 1602942}, {"name": "Senadores_da_Argentina", "id": 2860927}, {"name": "Senadores_da_República_Portuguesa", "id": 3558011}, {"name": "Senadores_do_Uruguai", "id": 4799410}, {"name": "Senadores_da_Polônia", "id": 5623469}, {"name": "Senadores_da_Espanha", "id": 5793700}, {"name": "Senadores_biônicos_do_Brasil", "id": 2256813}, {"name": "Presidentes_do_Senado_Federal_do_Brasil", "id": 3061696}, {"name": "Senadores_suplentes_do_Brasil", "id": 3454080}, {"name": "Senadores_da_Assembleia_Nacional_Constituinte_de_1987–1988", "id": 4131627}, {"name": "Senadores_da_Assembleia_Nacional_Constituinte_de_1946", "id": 5604323}, {"name": "Senadores_dos_Estados_Unidos_por_Massachusetts", "id": 4795948}, {"name": "Senadores_dos_Estados_Unidos_por_Nova_Iorque", "id": 4795953}, {"name": "Senadores_dos_Estados_Unidos_pelo_Kentucky", "id": 5454979}, {"name": "Senadores_dos_Estados_Unidos_pelo_Tennessee", "id": 5455022}, {"name": "Senadores_do_Império_do_Brasil_por_Minas_Gerais", "id": 3231942}, {"name": "Senadores_do_Império_do_Brasil_pelo_Rio_de_Janeiro", "id": 3232000}, {"name": "Senadores_do_Império_do_Brasil_pela_Bahia", "id": 3232007}, {"name": "Câmara_dos_Deputados_do_Brasil", "id": 2515270}, {"name": "Presidentes_do_Parlamento_Europeu", "id": 1937622}, {"name": "Deputados_do_Reino_de_Portugal", "id": 3837256}, {"name": "Deputados_da_República_Portuguesa", "id": 3841271}, {"name": "Deputados_da_Assembleia_Regional_da_Madeira", "id": 4714411}, {"name": "Deputados_da_Assembleia_Regional_dos_Açores", "id": 4714412}, {"name": "Membros_do_Parlamento_da_Noruega", "id": 3326600}, {"name": "Membros_do_Parlamento_do_Reino_Unido", "id": 3501088}, {"name": "Membros_do_Reichstag_da_Alemanha_Nazista", "id": 4415173}, {"name": "Membros_do_Parlamento_da_Finlândia", "id": 6892670}, {"name": "Membros_da_Câmara_dos_Representantes_dos_Estados_Unidos", "id": 2524009}, {"name": "Membros_da_Câmara_dos_Representantes_da_Austrália", "id": 3633495}, {"name": "Deputados_do_Congresso_dos_Deputados_da_Espanha", "id": 5793683}, {"name": "Membros_da_Câmara_de_Deputados_da_Nação_Argentina", "id": 6893933}, {"name": "Presidentes_da_Câmara_dos_Deputados_do_Brasil", "id": 3061664}, {"name": "Presidentes_da_Câmara_dos_Representantes_dos_Estados_Unidos", "id": 5433577}, {"name": "Membros_da_Câmara_de_Representantes_de_Massachusetts", "id": 3482586}, {"name": "Membros_do_Bundestag_1949-1953", "id": 6489737}, {"name": "Membros_do_Bundestag_1994-1998", "id": 6490014}, {"name": "Membros_do_Bundestag_2017-2021", "id": 6729842}, {"name": "Membros_do_Bundestag_2021-2025", "id": 6729843}, {"name": "Vereadores_de_câmaras_municipais_de_Portugal", "id": 4746595}, {"name": "Deputados_da_Assembleia_da_República_Portuguesa", "id": 4879658}, {"name": "Deputados_do_Parlamento_da_Catalunha", "id": 5572903}, {"name": "Parlamentares_do_Mercosul_pelo_Brasil", "id": 5121960}]}